database_to_bigquery/__init__.py
database_to_bigquery/base.py
database_to_bigquery/sql_server.py
database_to_bigquery-1.0.2.dist-info/LICENSE
database_to_bigquery-1.0.2.dist-info/METADATA
database_to_bigquery-1.0.2.dist-info/WHEEL
database_to_bigquery-1.0.2.dist-info/top_level.txt
database_to_bigquery-1.0.2.dist-info/RECORD
