Metadata-Version: 2.1
Name: database-to-bigquery
Version: 1.0.2
Summary: Read from SQL server and load to Google BigQuery
Home-page: https://github.com/ael-computas/sqlserver-to-bigquery
Author: Anders Elton
License: Apache 2.0
Download-URL: https://github.com/ael-computas/sqlserver-to-bigquery
Keywords: gcp,BigQuery,SQL Server,integration,copy
Platform: UNKNOWN
Classifier: Programming Language :: Python :: 3
Classifier: License :: OSI Approved :: Apache Software License
Classifier: Operating System :: OS Independent
License-File: LICENSE
Requires-Dist: python-dateutil (>=2.8.2)
Requires-Dist: google-cloud-storage (>=1.37.1)
Requires-Dist: google-cloud-bigquery (>=2.13.1)
Requires-Dist: smart-open[gcs] (>=5.0.0)
Requires-Dist: pyodbc (>=4.0.30)
Requires-Dist: sqlalchemy (>=1.4.10)
Requires-Dist: backoff (>=1.10.0)
Requires-Dist: google-cloud-secret-manager (>=2.4.0)
Requires-Dist: PyYAML (>=5.4.1)
